dehtml/__init__.py
dehtml/main.py
novel-dehtml/__init__.py
novel-dehtml/main.py
text-dehtml/__init__.py
text-dehtml/main.py
novel_dehtml-0.1.2.dist-info/LICENSE
novel_dehtml-0.1.2.dist-info/METADATA
novel_dehtml-0.1.2.dist-info/WHEEL
novel_dehtml-0.1.2.dist-info/entry_points.txt
novel_dehtml-0.1.2.dist-info/top_level.txt
novel_dehtml-0.1.2.dist-info/RECORD
